alt_logging_utils/__init__.py
alt_logging_utils/constants.py
alt_logging_utils/core.py
alt_logging_utils/exceptions.py
alt_logging_utils/py.typed
alt_logging_utils-0.1.0.dist-info/licenses/LICENSE
alt_logging_utils-0.1.0.dist-info/METADATA
alt_logging_utils-0.1.0.dist-info/WHEEL
alt_logging_utils-0.1.0.dist-info/top_level.txt
alt_logging_utils-0.1.0.dist-info/RECORD
